pyotita/__init__.py
pyotita/py.typed
pyotita-0.0.1.dist-info/METADATA
pyotita-0.0.1.dist-info/WHEEL
pyotita-0.0.1.dist-info/licenses/LICENSE
pyotita-0.0.1.dist-info/RECORD
