Metadata-Version: 2.4
Name: pyotita
Version: 0.0.1
Summary: A Code Quality Checker
Author-email: Markus Feiks <pypi.packages@feyx.de>
License-File: LICENSE
Requires-Python: >=3.11
